sgs/__init__.py
sgs/parser.py
sgsanitizer-1.0.1.data/scripts/sgsanitizer
sgsanitizer-1.0.1.dist-info/LICENSE.txt
sgsanitizer-1.0.1.dist-info/METADATA
sgsanitizer-1.0.1.dist-info/WHEEL
sgsanitizer-1.0.1.dist-info/top_level.txt
sgsanitizer-1.0.1.dist-info/RECORD
